{
  "attension-sign": {
    "height": 256,
    "pixelRatio": 2,
    "width": 256,
    "x": 0,
    "y": 0
  },
  "cattle_grid": {
    "height": 256,
    "pixelRatio": 2,
    "width": 256,
    "x": 0,
    "y": 256
  },
  "caution-sign": {
    "height": 256,
    "pixelRatio": 2,
    "width": 256,
    "x": 0,
    "y": 512
  },
  "cycle_barrier": {
    "height": 256,
    "pixelRatio": 2,
    "width": 256,
    "x": 1536,
    "y": 512
  },
  "drinking-water": {
    "height": 256,
    "pixelRatio": 2,
    "width": 256,
    "x": 0,
    "y": 768
  },
  "fallen_tree": {
    "height": 256,
    "pixelRatio": 2,
    "width": 256,
    "x": 256,
    "y": 0
  },
  "fence": {
    "height": 256,
    "pixelRatio": 2,
    "width": 256,
    "x": 256,
    "y": 256
  },
  "ford": {
    "height": 256,
    "pixelRatio": 2,
    "width": 256,
    "x": 256,
    "y": 512
  },
  "horse_no": {
    "height": 256,
    "pixelRatio": 2,
    "width": 256,
    "x": 256,
    "y": 768
  },
  "horse_restaurant_marker": {
    "height": 256,
    "pixelRatio": 2,
    "width": 256,
    "x": 512,
    "y": 0
  },
  "shelter": {
    "height": 256,
    "pixelRatio": 2,
    "width": 256,
    "x": 512,
    "y": 256
  },
  "stile": {
    "height": 256,
    "pixelRatio": 2,
    "width": 256,
    "x": 512,
    "y": 512
  },
  "trail_riding_station_marker2": {
    "height": 256,
    "pixelRatio": 2,
    "width": 256,
    "x": 512,
    "y": 768
  },
  "watering_place": {
    "height": 256,
    "pixelRatio": 2,
    "width": 256,
    "x": 768,
    "y": 0
  },
  "Barrier_cattle_grid-14": {
    "height": 256,
    "pixelRatio": 2,
    "width": 256,
    "x": 768,
    "y": 256
  },
  "Biergarten": {
    "height": 256,
    "pixelRatio": 2,
    "width": 256,
    "x": 768,
    "y": 512
  },
  "Burg": {
    "height": 256,
    "pixelRatio": 2,
    "width": 86,
    "x": 1792,
    "y": 512
  },
  "Schloss": {
    "height": 256,
    "pixelRatio": 2,
    "width": 256,
    "x": 1536,
    "y": 768
  },
  "Tower_observation": {
    "height": 256,
    "pixelRatio": 2,
    "width": 256,
    "x": 768,
    "y": 768
  },
  "Vetlogo": {
    "height": 256,
    "pixelRatio": 2,
    "width": 256,
    "x": 1024,
    "y": 0
  },
  "amenity_restaurant": {
    "height": 256,
    "pixelRatio": 2,
    "width": 256,
    "x": 1280,
    "y": 0
  },
  "attension-sign": {
    "height": 256,
    "pixelRatio": 2,
    "width": 256,
    "x": 1536,
    "y": 0
  },
  "castle": {
    "height": 256,
    "pixelRatio": 2,
    "width": 256,
    "x": 1792,
    "y": 0
  },
  "caution-sign1": {
    "height": 256,
    "pixelRatio": 2,
    "width": 256,
    "x": 1024,
    "y": 256
  },
  "fence": {
    "height": 256,
    "pixelRatio": 2,
    "width": 256,
    "x": 512,
    "y": 256
  },
  "fire2": {
    "height": 256,
    "pixelRatio": 2,
    "width": 256,
    "x": 1024,
    "y": 768
  },
  "ford1": {
    "height": 256,
    "pixelRatio": 2,
    "width": 256,
    "x": 1280,
    "y": 256
  },
  "horse3": {
    "height": 256,
    "pixelRatio": 2,
    "width": 256,
    "x": 1536,
    "y": 256
  },
  "map-picnic": {
    "height": 256,
    "pixelRatio": 2,
    "width": 256,
    "x": 1792,
    "y": 256
  },
  "no-entry-sign": {
    "height": 256,
    "pixelRatio": 2,
    "width": 256,
    "x": 1280,
    "y": 512
  },
  "windmill_03": {
    "height": 256,
    "pixelRatio": 2,
    "width": 256,
    "x": 1280,
    "y": 768
  }
}